xotl.crdt-0.2.0-py2.7-nspkg.pth
xotl/crdt/__init__.py
xotl/crdt/base.py
xotl/crdt/clocks.py
xotl/crdt/counter.py
xotl/crdt/register.py
xotl/crdt/release.py
xotl/crdt/sets.py
xotl/crdt/testing/__init__.py
xotl/crdt/testing/base.py
xotl/crdt/testing/counters.py
xotl/crdt/testing/registers.py
xotl/crdt/testing/sets.py
xotl.crdt-0.2.0.dist-info/DESCRIPTION.rst
xotl.crdt-0.2.0.dist-info/METADATA
xotl.crdt-0.2.0.dist-info/RECORD
xotl.crdt-0.2.0.dist-info/WHEEL
xotl.crdt-0.2.0.dist-info/metadata.json
xotl.crdt-0.2.0.dist-info/namespace_packages.txt
xotl.crdt-0.2.0.dist-info/top_level.txt
