Metadata-Version: 2.0
Name: xotl.crdt
Version: 0.2.0
Summary: CRDTs for Python
Home-page: https://gitlab.merchise.org/merchise/xotl.crdt
Author: Manuel Vázquez Acosta
Author-email: info@merchise.org
License: GPLv3
Project-URL: tracker, https://gitlab.merchise.org/merchise/xotl.crdt
Platform: UNKNOWN
Classifier: Programming Language :: Python
Requires-Python: >=3.6
Requires-Dist: xoutil (>=1.9.7)
Requires-Dist: decorator (<5,>=4)
Requires-Dist: dataclasses; python_version < "3.7"
